PyXplore/WPEM.py
PyXplore/__init__.py
PyXplore/Background/BacDeduct.py
PyXplore/Background/__init__.py
PyXplore/EMBraggOpt/BraggLawDerivation.py
PyXplore/EMBraggOpt/EMBraggSolver.py
PyXplore/EMBraggOpt/__init__.py
PyXplore/EMBraggOpt/WPEMFuns/SolverFuns.py
PyXplore/EMBraggOpt/WPEMFuns/__init__.py
PyXplore/Extinction/CifReader.py
PyXplore/Extinction/Relaxer.py
PyXplore/Extinction/XRDpre.py
PyXplore/Extinction/__init__.py
PyXplore/Extinction/m3gnet/__init__.py
PyXplore/Extinction/m3gnet/callbacks.py
PyXplore/Extinction/m3gnet/cli.py
PyXplore/Extinction/m3gnet/config.py
PyXplore/Extinction/m3gnet/type.py
PyXplore/Extinction/m3gnet/graph/__init__.py
PyXplore/Extinction/m3gnet/graph/_batch.py
PyXplore/Extinction/m3gnet/graph/_compute.py
PyXplore/Extinction/m3gnet/graph/_converters.py
PyXplore/Extinction/m3gnet/graph/_structure.py
PyXplore/Extinction/m3gnet/graph/_types.py
PyXplore/Extinction/m3gnet/layers/__init__.py
PyXplore/Extinction/m3gnet/layers/_aggregate.py
PyXplore/Extinction/m3gnet/layers/_atom.py
PyXplore/Extinction/m3gnet/layers/_atom_ref.py
PyXplore/Extinction/m3gnet/layers/_base.py
PyXplore/Extinction/m3gnet/layers/_basis.py
PyXplore/Extinction/m3gnet/layers/_bond.py
PyXplore/Extinction/m3gnet/layers/_core.py
PyXplore/Extinction/m3gnet/layers/_cutoff.py
PyXplore/Extinction/m3gnet/layers/_gn.py
PyXplore/Extinction/m3gnet/layers/_readout.py
PyXplore/Extinction/m3gnet/layers/_state.py
PyXplore/Extinction/m3gnet/layers/_three_body.py
PyXplore/Extinction/m3gnet/layers/_two_body.py
PyXplore/Extinction/m3gnet/models/__init__.py
PyXplore/Extinction/m3gnet/models/_base.py
PyXplore/Extinction/m3gnet/models/_dynamics.py
PyXplore/Extinction/m3gnet/models/_m3gnet.py
PyXplore/Extinction/m3gnet/trainers/__init__.py
PyXplore/Extinction/m3gnet/trainers/_metrics.py
PyXplore/Extinction/m3gnet/trainers/_potential.py
PyXplore/Extinction/m3gnet/trainers/_property.py
PyXplore/Extinction/m3gnet/utils/__init__.py
PyXplore/Extinction/m3gnet/utils/_general.py
PyXplore-2025.7.17.dist-info/METADATA
PyXplore-2025.7.17.dist-info/WHEEL
PyXplore-2025.7.17.dist-info/top_level.txt
PyXplore-2025.7.17.dist-info/RECORD
