Metadata-Version: 2.1
Name: PyXplore
Version: 2025.7.17
Summary: Toolkit for refining crystal structures using WPEM
Home-page: https://github.com/Bin-Cao/PyWPEM
Author: Bin CAO
Author-email: bincao4-c@my.cityu.edu.hk
Maintainer: Bin CAO
Maintainer-email: bincao4-c@my.cityu.edu.hk
License: MIT License
Classifier: Development Status :: 3 - Alpha
Classifier: Intended Audience :: Science/Research
Classifier: Topic :: Scientific/Engineering :: Chemistry
Classifier: Topic :: Scientific/Engineering :: Artificial Intelligence
Classifier: License :: OSI Approved :: MIT License
Classifier: Programming Language :: Python :: 3
Classifier: Programming Language :: Python :: 3.6
Classifier: Programming Language :: Python :: 3.7
Classifier: Programming Language :: Python :: 3.8
Classifier: Programming Language :: Python :: 3.9
Classifier: Programming Language :: Python :: 3.10
Requires-Python: >=3.6
Requires-Dist: numpy
Requires-Dist: matplotlib
Requires-Dist: scipy
Requires-Dist: pymatgen
